ergo_pytorch-1.1.1.dist-info/DESCRIPTION.rst
ergo_pytorch-1.1.1.dist-info/METADATA
ergo_pytorch-1.1.1.dist-info/RECORD
ergo_pytorch-1.1.1.dist-info/WHEEL
ergo_pytorch-1.1.1.dist-info/metadata.json
ergo_pytorch-1.1.1.dist-info/top_level.txt
ergonomics/__init__.py
ergonomics/algorithmia.py
ergonomics/serialization.py
