Metadata-Version: 2.0
Name: ergo-pytorch
Version: 1.1.1
Summary: making torch even better.
Home-page: UNKNOWN
Author: Algorithmia
Maintainer: Algorithmia
License: MIT
Platform: UNKNOWN
Classifier: Development Status :: 4 - Beta
Classifier: Intended Audience :: Developers
Classifier: Natural Language :: English
Classifier: License :: OSI Approved :: MIT License
Classifier: Operating System :: OS Independent
Classifier: Programming Language :: Python
Classifier: Programming Language :: Python :: 3
Classifier: Programming Language :: Python :: 3.3
Classifier: Topic :: Software Development :: Libraries :: Python Modules
